{
  "id": "notes-api-environment",
  "name": "Week06 Notes API - Local",
  "values": [
    {
      "key": "baseUrl",
      "value": "http://localhost:8081",
      "type": "default",
      "enabled": true
    },
    {
      "key": "apiPath",
      "value": "/api",
      "type": "default",
      "enabled": true
    },
    {
      "key": "noteId",
      "value": "68eb21c8ac884968425cbe16",
      "type": "default",
      "enabled": true
    }
  ],
  "_postman_variable_scope": "environment",
  "_postman_exported_at": "2025-10-12T00:00:00.000Z",
  "_postman_exported_using": "Postman/10.0.0"
}
